pyplumio/__init__.py
pyplumio/__main__.py
pyplumio/_version.py
pyplumio/connection.py
pyplumio/const.py
pyplumio/data_types.py
pyplumio/exceptions.py
pyplumio/filters.py
pyplumio/protocol.py
pyplumio/py.typed
pyplumio/stream.py
pyplumio/utils.py
pyplumio/devices/__init__.py
pyplumio/devices/ecomax.py
pyplumio/devices/ecoster.py
pyplumio/devices/mixer.py
pyplumio/devices/thermostat.py
pyplumio/frames/__init__.py
pyplumio/frames/messages.py
pyplumio/frames/requests.py
pyplumio/frames/responses.py
pyplumio/helpers/__init__.py
pyplumio/helpers/async_cache.py
pyplumio/helpers/event_manager.py
pyplumio/helpers/task_manager.py
pyplumio/parameters/__init__.py
pyplumio/parameters/ecomax.py
pyplumio/parameters/mixer.py
pyplumio/parameters/thermostat.py
pyplumio/parameters/custom/__init__.py
pyplumio/parameters/custom/ecomax_860d3_hb.py
pyplumio/structures/__init__.py
pyplumio/structures/alerts.py
pyplumio/structures/ecomax_parameters.py
pyplumio/structures/frame_versions.py
pyplumio/structures/mixer_parameters.py
pyplumio/structures/network_info.py
pyplumio/structures/product_info.py
pyplumio/structures/program_version.py
pyplumio/structures/regulator_data.py
pyplumio/structures/regulator_data_schema.py
pyplumio/structures/schedules.py
pyplumio/structures/sensor_data.py
pyplumio/structures/thermostat_parameters.py
pyplumio-0.6.8.dist-info/licenses/LICENSE
pyplumio-0.6.8.dist-info/METADATA
pyplumio-0.6.8.dist-info/WHEEL
pyplumio-0.6.8.dist-info/top_level.txt
pyplumio-0.6.8.dist-info/RECORD
