Metadata-Version: 2.4
Name: PyPlumIO
Version: 0.6.8
Summary: PyPlumIO is a native ecoNET library for Plum ecoMAX controllers.
Author-email: Denis Paavilainen <denpa@denpa.pro>
License: MIT License
Project-URL: Documentation, https://pyplumio.denpa.pro
Project-URL: Source Code, https://github.com/denpamusic/PyPlumIO
Project-URL: Bug Tracker, https://github.com/denpamusic/PyPlumIO/issues
Keywords: home,automation,heating
Platform: any
Classifier: Development Status :: 4 - Beta
Classifier: Intended Audience :: Developers
Classifier: License :: OSI Approved :: MIT License
Classifier: Operating System :: OS Independent
Classifier: Programming Language :: Python :: 3.10
Classifier: Programming Language :: Python :: 3.11
Classifier: Programming Language :: Python :: 3.12
Classifier: Programming Language :: Python :: 3.13
Classifier: Programming Language :: Python :: 3.14
Classifier: Topic :: Software Development :: Libraries
Classifier: Topic :: Home Automation
Requires-Python: >=3.10
License-File: LICENSE
Requires-Dist: pyserial-asyncio-fast==0.16
Provides-Extra: test
Requires-Dist: codespell==2.4.1; extra == "test"
Requires-Dist: coverage==7.13.0; extra == "test"
Requires-Dist: freezegun==1.5.5; extra == "test"
Requires-Dist: mypy==1.19.1; extra == "test"
Requires-Dist: numpy<3.0.0,>=2.0.0; extra == "test"
Requires-Dist: pyserial-asyncio-fast==0.16; extra == "test"
Requires-Dist: pytest==9.0.2; extra == "test"
Requires-Dist: pytest-asyncio==1.3.0; extra == "test"
Requires-Dist: ruff==0.14.10; extra == "test"
Requires-Dist: tox==4.32.0; extra == "test"
Requires-Dist: types-pyserial==3.5.0.20251001; extra == "test"
Provides-Extra: docs
Requires-Dist: sphinx==8.1.3; extra == "docs"
Requires-Dist: sphinx_rtd_theme==3.0.2; extra == "docs"
Requires-Dist: readthedocs-sphinx-search==0.3.2; extra == "docs"
Provides-Extra: dev
Requires-Dist: pyplumio[docs,test]; extra == "dev"
Requires-Dist: pre-commit==4.5.1; extra == "dev"
Requires-Dist: tomli==2.3.0; extra == "dev"
Dynamic: license-file
